{"generatedAt":"17/05/2026 10:53:41","updatedAt":"17/05/2026 10:53","headers":["VESSEL & VOYAGE","CODE RNR","MANIFEST","DG & AWKWARD DOCS","DOCS CLOSING & FINAL SI","ENTER TO PORT","ETA","REMARKS 1","REMARKS 2"],"rows":[{"line":"1 // MD1 - ASHDOD TO FAR EAST EXCLUDING PUSAN, XINGANG, DALIAN // USEC VIA PIRAEUS","cells":["YM WARMTH 0043E","0353","260117","CLOSED","10/05/2026 - 08:30","10/05/2026 - 22:00","10/05/2026","MD1","SUBJECT TO CHANGE"],"updatedAt":"10/05/2026 09:03","updatedAtMs":1778392984036},{"line":"1 // MD1 - ASHDOD TO FAR EAST EXCLUDING PUSAN, XINGANG, DALIAN // USEC VIA PIRAEUS","cells":["YM WISH 0050E","0360","260118","11/05/2026 - 10:00","13/05/2026 - 12:00","15/05/2026 - 10:00","17/05/2026","MD1","SUBJECT TO CHANGE"],"updatedAt":"07/05/2026 17:54","updatedAtMs":1778165648692},{"line":"1 // MD1 - ASHDOD TO FAR EAST EXCLUDING PUSAN, XINGANG, DALIAN // USEC VIA PIRAEUS","cells":["YM WORLD 0048E","0174","260119","18/05/2026 - 10:00","20/05/2026 - 12:00","22/05/2026 - 10:00","24/05/2026","MD1555","SUBJECT TO CHANGE"],"updatedAt":"17/05/2026 10:53","updatedAtMs":1779004413047},{"line":"1 // MD1 - ASHDOD TO FAR EAST EXCLUDING PUSAN, XINGANG, DALIAN // USEC VIA PIRAEUS","cells":["YM WISDOM 0026E","5480","TBA","25/05/2026 - 10:00","27/05/2026 - 12:00","29/05/2026 - 10:00","30/05/2026","MD1","SUBJECT TO CHANGE"],"updatedAt":"08/05/2026 09:32","updatedAtMs":1778221970139},{"line":"2 // AD1 - ASHDOD ADRIATIC DIRECT & NORTHEN EUROPE VIA DAMIETTA","cells":["CHATTANOOGA 0051W","0723","TBA","CLOSED","13/05/2026 - 10;00","14/05/2026 - 10:00","15/05/2026","AD1","SUBJECT TO CHANGE"],"updatedAt":"10/05/2026 09:03","updatedAtMs":1778392995335},{"line":"2 // AD1 - ASHDOD ADRIATIC DIRECT & NORTHEN EUROPE VIA DAMIETTA","cells":["MITO 0062W","2473","TBA","12/05/2026 - 10:00","18/05/2026 - 10:00","19/05/2026 - 10:00","20/05/2026","AD1 - GRPIR ONLY","SUBJECT TO CHANGE"],"updatedAt":"08/05/2026 09:26","updatedAtMs":1778221599915},{"line":"2 // AD1 - ASHDOD ADRIATIC DIRECT & NORTHEN EUROPE VIA DAMIETTA","cells":["MITO 0063W","2473","TBA","20/05/2026 - 10:00","25/05/2026 - 10:00","26/05/2026 - 10:00","27/05/2026","AD1","SUBJECT TO CHANGE"],"updatedAt":"08/05/2026 09:26","updatedAtMs":1778221600596},{"line":"2 // AD1 - ASHDOD ADRIATIC DIRECT & NORTHEN EUROPE VIA DAMIETTA","cells":["ADMIRAL SUN 0009W","2648","TBA","26/05/2026 - 10:00","01/06/2026 - 10:00","02/06/2026 - 10:00","03/06/2026","AD1","SUBJECT TO CHANGE"],"updatedAt":"","updatedAtMs":0},{"line":"2 // AD1 - ASHDOD ADRIATIC DIRECT & NORTHEN EUROPE VIA DAMIETTA","cells":["CHATTANOOGA 0052W","0723","TBA","02/06/2026 - 10:00","08/06/2026 - 10:00","09/06/2026 - 10:00","10/06/2026","AD1","SUBJECT TO CHANGE"],"updatedAt":"","updatedAtMs":0},{"line":"3 // AD1 - HAIFA ADRIATIC DIRECT & NORTHEN EUROPE VIA DAMIETTA / INDIA & USEC VIA PIRAEUS","cells":["ADMIRAL SUN 0008W","2648","262205","CLOSED","CLOSED","CLOSED","ANCHOR","AD1","SUBJECT TO CHANGE"],"updatedAt":"10/05/2026 09:03","updatedAtMs":1778393007482},{"line":"3 // AD1 - HAIFA ADRIATIC DIRECT & NORTHEN EUROPE VIA DAMIETTA / INDIA & USEC VIA PIRAEUS","cells":["CHATTANOOGA 0051W","0723","TBA","CLOSED","12/05/2026 - 10;00","13/05/2026 - 10:00","14/05/2026","AD1","SUBJECT TO CHANGE"],"updatedAt":"08/05/2026 09:26","updatedAtMs":1778221607337},{"line":"3 // AD1 - HAIFA ADRIATIC DIRECT & NORTHEN EUROPE VIA DAMIETTA / INDIA & USEC VIA PIRAEUS","cells":["MITO 0062W","2473","TBA","12/05/2026 - 10:00","17/05/2026 - 10:00","18/05/2026 - 10:00","19/05/2026","AD1 - GRPIR ONLY","SUBJECT TO CHANGE"],"updatedAt":"10/05/2026 13:38","updatedAtMs":1778409537112},{"line":"3 // AD1 - HAIFA ADRIATIC DIRECT & NORTHEN EUROPE VIA DAMIETTA / INDIA & USEC VIA PIRAEUS","cells":["MITO 0063W","2473","TBA","19/05/2026 - 10:00","24/05/2026 - 10:00","25/05/2026 - 10:00","26/05/2026","AD1","SUBJECT TO CHANGE"],"updatedAt":"10/05/2026 13:38","updatedAtMs":1778409537326},{"line":"3 // AD1 - HAIFA ADRIATIC DIRECT & NORTHEN EUROPE VIA DAMIETTA / INDIA & USEC VIA PIRAEUS","cells":["ADMIRAL SUN 0009W","2648","TBA","26/05/2026 - 10:00","31/05/2026 - 10:00","01/06/2026 - 10:00","02/06/2026","AD1","SUBJECT TO CHANGE"],"updatedAt":"","updatedAtMs":0},{"line":"4 // LEX - HAIFA NORTHEN EUROPE & ALEXANDRIA / DAMIETTA  -  DIRECT SERVICE","cells":["JOHANNES MAERSK 0620N","TBA","TBA","IRRELEVANT","12/05/2026 - 10:00","13/05/2026 - 10:00","14/05/2026","LEX","SUBJECT TO CHANGE"],"updatedAt":"10/05/2026 09:03","updatedAtMs":1778393015003},{"line":"4 // LEX - HAIFA NORTHEN EUROPE & ALEXANDRIA / DAMIETTA  -  DIRECT SERVICE","cells":["VUOKSI MAERSK 0621N","TBA","TBA","IRRELEVANT","19/05/2026 - 10:00","20/05/2026 - 10:00","21/05/2026","LEX","SUBJECT TO CHANGE"],"updatedAt":"08/05/2026 09:26","updatedAtMs":1778221612545}]}